comments_cleaner/__init__.py
comments_cleaner/cpp.py
comments_cleaner/python.py
comments_cleaner_Tifa-0.0.3.dist-info/LICENSE
comments_cleaner_Tifa-0.0.3.dist-info/METADATA
comments_cleaner_Tifa-0.0.3.dist-info/WHEEL
comments_cleaner_Tifa-0.0.3.dist-info/top_level.txt
comments_cleaner_Tifa-0.0.3.dist-info/RECORD
