Metadata-Version: 2.1
Name: comments-cleaner-Tifa
Version: 0.0.3
Summary: Comments cleaner, Support C/C++, Python
Home-page: https://github.com/Tiphereth-A/cmcleaner
Author: Tifa
Author-email: tiphereth-a@qq.com
License: GNU General Public License v3.0
Project-URL: Bug Tracker, https://github.com/Tiphereth-A/cmcleaner/issues
Platform: UNKNOWN
Classifier: Programming Language :: Python :: 3
Classifier: Operating System :: OS Independent
Requires-Python: >=3.6
License-File: LICENSE
